CMakeLists.txt
LICENSE
MANIFEST.in
README.md
setup.cfg
setup.py
dtmpy/__init__.py
dtmpy/model.py
dtmpy.egg-info/PKG-INFO
dtmpy.egg-info/SOURCES.txt
dtmpy.egg-info/dependency_links.txt
dtmpy.egg-info/not-zip-safe
dtmpy.egg-info/requires.txt
dtmpy.egg-info/top_level.txt
src/CMakeLists.txt
src/dtm/CMakeLists.txt
src/dtm/data.cpp
src/dtm/data.hpp
src/dtm/dtm.cpp
src/dtm/dtm.hpp
src/dtm/flags.hpp
src/dtm/gsl-wrappers.cpp
src/dtm/gsl-wrappers.hpp
src/dtm/lda-seq.cpp
src/dtm/lda-seq.hpp
src/dtm/lda.cpp
src/dtm/lda.hpp
src/dtm/param.cpp
src/dtm/param.hpp
src/dtm/params.cpp
src/dtm/params.hpp
src/dtm/ss-lm.cpp
src/dtm/ss-lm.hpp
src/dtm/util.cpp
src/dtm/util.hpp
src/dtmpy/CMakeLists.txt
src/dtmpy/dtmpy.cpp