Metadata-Version: 2.1
Name: dtmpy
Version: 0.1.1
Summary: Fast Dynamic Topic Modeling with Python
Home-page: https://github.com/jeffmm/dtmpy.git
Author: Jeff Moore
Author-email: jmoore@manifold.ai
License: UNKNOWN
Platform: UNKNOWN
License-File: LICENSE
